fillargs/__init__.py
fillargs/arg_handler.py
fillargs/env.py
fillargs/utils.py
fillargs-1.0.1.dist-info/LICENSE
fillargs-1.0.1.dist-info/METADATA
fillargs-1.0.1.dist-info/WHEEL
fillargs-1.0.1.dist-info/top_level.txt
fillargs-1.0.1.dist-info/RECORD
